[
  {
    "experiment_name": "simple_pems-bay_GraphWaveNet_22_04_2026-17h_33-epoch_30",
    "model": "GraphWaveNet",
    "dataset": "pems-bay",
    "params": "{\"dilation_base\": 2, \"dropout\": 0.1, \"hidden_dim\": 64, \"k\": 2, \"lr\": 0.001, \"num_blocks\": 3, \"patience\": 5, \"weight_decay\": 0.0001}",
    "num_completed_seeds": 1,
    "seeds": [
      42
    ],
    "val_mae_mean": 2.172835350036621,
    "val_mae_std": 0.0,
    "val_mae_ci95_low": 2.172835350036621,
    "val_mae_ci95_high": 2.172835350036621,
    "val_mae_min": 2.172835350036621,
    "val_mae_max": 2.172835350036621,
    "val_mae_n": 1,
    "val_rmse_mean": 4.567534923553467,
    "val_rmse_std": 0.0,
    "val_rmse_ci95_low": 4.567534923553467,
    "val_rmse_ci95_high": 4.567534923553467,
    "val_rmse_min": 4.567534923553467,
    "val_rmse_max": 4.567534923553467,
    "val_rmse_n": 1,
    "val_mape_mean": 135216.15625,
    "val_mape_std": 0.0,
    "val_mape_ci95_low": 135216.15625,
    "val_mape_ci95_high": 135216.15625,
    "val_mape_min": 135216.15625,
    "val_mape_max": 135216.15625,
    "val_mape_n": 1,
    "val_smape_mean": 4.499558448791504,
    "val_smape_std": 0.0,
    "val_smape_ci95_low": 4.499558448791504,
    "val_smape_ci95_high": 4.499558448791504,
    "val_smape_min": 4.499558448791504,
    "val_smape_max": 4.499558448791504,
    "val_smape_n": 1,
    "val_wape_mean": 3.498654365539551,
    "val_wape_std": 0.0,
    "val_wape_ci95_low": 3.498654365539551,
    "val_wape_ci95_high": 3.498654365539551,
    "val_wape_min": 3.498654365539551,
    "val_wape_max": 3.498654365539551,
    "val_wape_n": 1,
    "val_loss_normalized_mean": 0.2356361907112635,
    "val_loss_normalized_std": 0.0,
    "val_loss_normalized_ci95_low": 0.2356361907112635,
    "val_loss_normalized_ci95_high": 0.2356361907112635,
    "val_loss_normalized_min": 0.2356361907112635,
    "val_loss_normalized_max": 0.2356361907112635,
    "val_loss_normalized_n": 1
  },
  {
    "experiment_name": "simple_pems-bay_MTGNN_22_04_2026-17h_33-epoch_30",
    "model": "MTGNN",
    "dataset": "pems-bay",
    "params": "{\"dilation_base\": 2, \"dropout\": 0.1, \"gcn_depth\": 2, \"hidden_dim\": 64, \"kernel_size\": 2, \"lr\": 0.001, \"node_dim\": 16, \"num_blocks\": 3, \"patience\": 5, \"propalpha\": 0.05, \"weight_decay\": 0.0001}",
    "num_completed_seeds": 1,
    "seeds": [
      42
    ],
    "val_mae_mean": 2.3527536392211914,
    "val_mae_std": 0.0,
    "val_mae_ci95_low": 2.3527536392211914,
    "val_mae_ci95_high": 2.3527536392211914,
    "val_mae_min": 2.3527536392211914,
    "val_mae_max": 2.3527536392211914,
    "val_mae_n": 1,
    "val_rmse_mean": 5.031579971313477,
    "val_rmse_std": 0.0,
    "val_rmse_ci95_low": 5.031579971313477,
    "val_rmse_ci95_high": 5.031579971313477,
    "val_rmse_min": 5.031579971313477,
    "val_rmse_max": 5.031579971313477,
    "val_rmse_n": 1,
    "val_mape_mean": 134245.859375,
    "val_mape_std": 0.0,
    "val_mape_ci95_low": 134245.859375,
    "val_mape_ci95_high": 134245.859375,
    "val_mape_min": 134245.859375,
    "val_mape_max": 134245.859375,
    "val_mape_n": 1,
    "val_smape_mean": 4.890611171722412,
    "val_smape_std": 0.0,
    "val_smape_ci95_low": 4.890611171722412,
    "val_smape_ci95_high": 4.890611171722412,
    "val_smape_min": 4.890611171722412,
    "val_smape_max": 4.890611171722412,
    "val_smape_n": 1,
    "val_wape_mean": 3.7883548736572266,
    "val_wape_std": 0.0,
    "val_wape_ci95_low": 3.7883548736572266,
    "val_wape_ci95_high": 3.7883548736572266,
    "val_wape_min": 3.7883548736572266,
    "val_wape_max": 3.7883548736572266,
    "val_wape_n": 1,
    "val_loss_normalized_mean": 0.286117496060356,
    "val_loss_normalized_std": 0.0,
    "val_loss_normalized_ci95_low": 0.286117496060356,
    "val_loss_normalized_ci95_high": 0.286117496060356,
    "val_loss_normalized_min": 0.286117496060356,
    "val_loss_normalized_max": 0.286117496060356,
    "val_loss_normalized_n": 1
  },
  {
    "experiment_name": "simple_pems-bay_STICformer_22_04_2026-17h_33-epoch_30",
    "model": "STICformer",
    "dataset": "pems-bay",
    "params": "{\"dropout\": 0.1, \"ff_multiplier\": 2, \"hidden_dim\": 64, \"lr\": 0.001, \"num_heads\": 4, \"num_layers\": 2, \"patience\": 5, \"weight_decay\": 0.0001}",
    "num_completed_seeds": 1,
    "seeds": [
      42
    ],
    "val_mae_mean": 2.073707342147827,
    "val_mae_std": 0.0,
    "val_mae_ci95_low": 2.073707342147827,
    "val_mae_ci95_high": 2.073707342147827,
    "val_mae_min": 2.073707342147827,
    "val_mae_max": 2.073707342147827,
    "val_mae_n": 1,
    "val_rmse_mean": 4.363852024078369,
    "val_rmse_std": 0.0,
    "val_rmse_ci95_low": 4.363852024078369,
    "val_rmse_ci95_high": 4.363852024078369,
    "val_rmse_min": 4.363852024078369,
    "val_rmse_max": 4.363852024078369,
    "val_rmse_n": 1,
    "val_mape_mean": 135731.390625,
    "val_mape_std": 0.0,
    "val_mape_ci95_low": 135731.390625,
    "val_mape_ci95_high": 135731.390625,
    "val_mape_min": 135731.390625,
    "val_mape_max": 135731.390625,
    "val_mape_n": 1,
    "val_smape_mean": 4.2932586669921875,
    "val_smape_std": 0.0,
    "val_smape_ci95_low": 4.2932586669921875,
    "val_smape_ci95_high": 4.2932586669921875,
    "val_smape_min": 4.2932586669921875,
    "val_smape_max": 4.2932586669921875,
    "val_smape_n": 1,
    "val_wape_mean": 3.339040756225586,
    "val_wape_std": 0.0,
    "val_wape_ci95_low": 3.339040756225586,
    "val_wape_ci95_high": 3.339040756225586,
    "val_wape_min": 3.339040756225586,
    "val_wape_max": 3.339040756225586,
    "val_wape_n": 1,
    "val_loss_normalized_mean": 0.215442148614332,
    "val_loss_normalized_std": 0.0,
    "val_loss_normalized_ci95_low": 0.215442148614332,
    "val_loss_normalized_ci95_high": 0.215442148614332,
    "val_loss_normalized_min": 0.215442148614332,
    "val_loss_normalized_max": 0.215442148614332,
    "val_loss_normalized_n": 1
  },
  {
    "experiment_name": "simple_metr-la_GraphWaveNet_22_04_2026-17h_33-epoch_30",
    "model": "GraphWaveNet",
    "dataset": "metr-la",
    "params": "{\"dilation_base\": 2, \"dropout\": 0.1, \"hidden_dim\": 64, \"k\": 2, \"lr\": 0.001, \"num_blocks\": 3, \"patience\": 5, \"weight_decay\": 0.0001}",
    "num_completed_seeds": 1,
    "seeds": [
      42
    ],
    "val_mae_mean": 5.388321399688721,
    "val_mae_std": 0.0,
    "val_mae_ci95_low": 5.388321399688721,
    "val_mae_ci95_high": 5.388321399688721,
    "val_mae_min": 5.388321399688721,
    "val_mae_max": 5.388321399688721,
    "val_mae_n": 1,
    "val_rmse_mean": 11.005603790283203,
    "val_rmse_std": 0.0,
    "val_rmse_ci95_low": 11.005603790283203,
    "val_rmse_ci95_high": 11.005603790283203,
    "val_rmse_min": 11.005603790283203,
    "val_rmse_max": 11.005603790283203,
    "val_rmse_n": 1,
    "val_mape_mean": 11188715520.0,
    "val_mape_std": 0.0,
    "val_mape_ci95_low": 11188715520.0,
    "val_mape_ci95_high": 11188715520.0,
    "val_mape_min": 11188715520.0,
    "val_mape_max": 11188715520.0,
    "val_mape_n": 1,
    "val_smape_mean": 23.54511070251465,
    "val_smape_std": 0.0,
    "val_smape_ci95_low": 23.54511070251465,
    "val_smape_ci95_high": 23.54511070251465,
    "val_smape_min": 23.54511070251465,
    "val_smape_max": 23.54511070251465,
    "val_smape_n": 1,
    "val_wape_mean": 9.825498580932617,
    "val_wape_std": 0.0,
    "val_wape_ci95_low": 9.825498580932617,
    "val_wape_ci95_high": 9.825498580932617,
    "val_wape_min": 9.825498580932617,
    "val_wape_max": 9.825498580932617,
    "val_wape_n": 1,
    "val_loss_normalized_mean": 0.31774675017483883,
    "val_loss_normalized_std": 0.0,
    "val_loss_normalized_ci95_low": 0.31774675017483883,
    "val_loss_normalized_ci95_high": 0.31774675017483883,
    "val_loss_normalized_min": 0.31774675017483883,
    "val_loss_normalized_max": 0.31774675017483883,
    "val_loss_normalized_n": 1
  },
  {
    "experiment_name": "simple_metr-la_MTGNN_22_04_2026-17h_33-epoch_30",
    "model": "MTGNN",
    "dataset": "metr-la",
    "params": "{\"dilation_base\": 2, \"dropout\": 0.1, \"gcn_depth\": 2, \"hidden_dim\": 64, \"kernel_size\": 2, \"lr\": 0.001, \"node_dim\": 16, \"num_blocks\": 3, \"patience\": 5, \"propalpha\": 0.05, \"weight_decay\": 0.0001}",
    "num_completed_seeds": 1,
    "seeds": [
      42
    ],
    "val_mae_mean": 5.849453449249268,
    "val_mae_std": 0.0,
    "val_mae_ci95_low": 5.849453449249268,
    "val_mae_ci95_high": 5.849453449249268,
    "val_mae_min": 5.849453449249268,
    "val_mae_max": 5.849453449249268,
    "val_mae_n": 1,
    "val_rmse_mean": 11.221933364868164,
    "val_rmse_std": 0.0,
    "val_rmse_ci95_low": 11.221933364868164,
    "val_rmse_ci95_high": 11.221933364868164,
    "val_rmse_min": 11.221933364868164,
    "val_rmse_max": 11.221933364868164,
    "val_rmse_n": 1,
    "val_mape_mean": 13322028032.0,
    "val_mape_std": 0.0,
    "val_mape_ci95_low": 13322028032.0,
    "val_mape_ci95_high": 13322028032.0,
    "val_mape_min": 13322028032.0,
    "val_mape_max": 13322028032.0,
    "val_mape_n": 1,
    "val_smape_mean": 24.120214462280273,
    "val_smape_std": 0.0,
    "val_smape_ci95_low": 24.120214462280273,
    "val_smape_ci95_high": 24.120214462280273,
    "val_smape_min": 24.120214462280273,
    "val_smape_max": 24.120214462280273,
    "val_smape_n": 1,
    "val_wape_mean": 10.666363716125488,
    "val_wape_std": 0.0,
    "val_wape_ci95_low": 10.666363716125488,
    "val_wape_ci95_high": 10.666363716125488,
    "val_wape_min": 10.666363716125488,
    "val_wape_max": 10.666363716125488,
    "val_wape_n": 1,
    "val_loss_normalized_mean": 0.33040779726318664,
    "val_loss_normalized_std": 0.0,
    "val_loss_normalized_ci95_low": 0.33040779726318664,
    "val_loss_normalized_ci95_high": 0.33040779726318664,
    "val_loss_normalized_min": 0.33040779726318664,
    "val_loss_normalized_max": 0.33040779726318664,
    "val_loss_normalized_n": 1
  },
  {
    "experiment_name": "simple_metr-la_STICformer_22_04_2026-17h_33-epoch_30",
    "model": "STICformer",
    "dataset": "metr-la",
    "params": "{\"dropout\": 0.1, \"ff_multiplier\": 2, \"hidden_dim\": 64, \"lr\": 0.001, \"num_heads\": 4, \"num_layers\": 2, \"patience\": 5, \"weight_decay\": 0.0001}",
    "num_completed_seeds": 1,
    "seeds": [
      42
    ],
    "val_mae_mean": 5.187530994415283,
    "val_mae_std": 0.0,
    "val_mae_ci95_low": 5.187530994415283,
    "val_mae_ci95_high": 5.187530994415283,
    "val_mae_min": 5.187530994415283,
    "val_mae_max": 5.187530994415283,
    "val_mae_n": 1,
    "val_rmse_mean": 10.798018455505371,
    "val_rmse_std": 0.0,
    "val_rmse_ci95_low": 10.798018455505371,
    "val_rmse_ci95_high": 10.798018455505371,
    "val_rmse_min": 10.798018455505371,
    "val_rmse_max": 10.798018455505371,
    "val_rmse_n": 1,
    "val_mape_mean": 11997708288.0,
    "val_mape_std": 0.0,
    "val_mape_ci95_low": 11997708288.0,
    "val_mape_ci95_high": 11997708288.0,
    "val_mape_min": 11997708288.0,
    "val_mape_max": 11997708288.0,
    "val_mape_n": 1,
    "val_smape_mean": 23.09780502319336,
    "val_smape_std": 0.0,
    "val_smape_ci95_low": 23.09780502319336,
    "val_smape_ci95_high": 23.09780502319336,
    "val_smape_min": 23.09780502319336,
    "val_smape_max": 23.09780502319336,
    "val_smape_n": 1,
    "val_wape_mean": 9.45936107635498,
    "val_wape_std": 0.0,
    "val_wape_ci95_low": 9.45936107635498,
    "val_wape_ci95_high": 9.45936107635498,
    "val_wape_min": 9.45936107635498,
    "val_wape_max": 9.45936107635498,
    "val_wape_n": 1,
    "val_loss_normalized_mean": 0.30588421422257045,
    "val_loss_normalized_std": 0.0,
    "val_loss_normalized_ci95_low": 0.30588421422257045,
    "val_loss_normalized_ci95_high": 0.30588421422257045,
    "val_loss_normalized_min": 0.30588421422257045,
    "val_loss_normalized_max": 0.30588421422257045,
    "val_loss_normalized_n": 1
  }
]